basketball_cleaner/__init__.py
basketball_cleaner/cleaner.py
basketball_cleaner-0.1.4.dist-info/METADATA
basketball_cleaner-0.1.4.dist-info/WHEEL
basketball_cleaner-0.1.4.dist-info/top_level.txt
basketball_cleaner-0.1.4.dist-info/RECORD
