Metadata-Version: 2.4
Name: basketball-cleaner
Version: 0.1.4
Summary: Fill null basketball stats ratios for your dataset
Author: Ananya Srinivas
License: MIT
Project-URL: Homepage, https://github.com/yourusername/basketball-cleaner
Keywords: basketball,data-cleaning,sports-analytics
Classifier: Programming Language :: Python :: 3
Classifier: License :: OSI Approved :: MIT License
Classifier: Operating System :: OS Independent
Requires-Python: >=3.8
